requirements.txt
douyin/__init__.py
douyin/__version__.py
douyin/config.py
douyin/downloader/__init__.py
douyin/downloaders/__init__.py
douyin/downloaders/base.py
douyin/downloaders/music.py
douyin/downloaders/video.py
douyin/handlers/__init__.py
douyin/handlers/base.py
douyin/handlers/file.py
douyin/handlers/mongo.py
douyin/handlers/music.py
douyin/handlers/video.py
douyin/hot/__init__.py
douyin/hot/energy.py
douyin/hot/music.py
douyin/hot/search.py
douyin/hot/trend.py
douyin/hot/video.py
douyin/structure/__init__.py
douyin/structure/address.py
douyin/structure/hot.py
douyin/structure/music.py
douyin/structure/user.py
douyin/structure/video.py
douyin/structures/__init__.py
douyin/structures/address.py
douyin/structures/base.py
douyin/structures/hot.py
douyin/structures/music.py
douyin/structures/topic.py
douyin/structures/user.py
douyin/structures/video.py
douyin/utils/__init__.py
douyin/utils/common.py
douyin/utils/fetch.py
douyin/utils/parse.py
douyin/utils/tranform.py
douyin/utils/type.py
douyin-0.3.6.dist-info/DESCRIPTION.rst
douyin-0.3.6.dist-info/METADATA
douyin-0.3.6.dist-info/RECORD
douyin-0.3.6.dist-info/WHEEL
douyin-0.3.6.dist-info/metadata.json
douyin-0.3.6.dist-info/top_level.txt
