Metadata-Version: 2.0
Name: douyin
Version: 0.3.6
Summary: Api of douyin for humans
Home-page: https://github.com/Germey/Douyin
Author: Germey
Author-email: cqc@cuiqingcai.com
License: MIT
Platform: UNKNOWN
Classifier: License :: OSI Approved :: MIT License
Classifier: Programming Language :: Python
Classifier: Programming Language :: Python :: 3
Classifier: Programming Language :: Python :: 3.6
Classifier: Programming Language :: Python :: Implementation :: CPython
Classifier: Programming Language :: Python :: Implementation :: PyPy
Requires-Python: >=3.4.0
Requires-Dist: aiohttp (>=3.4.4)
Requires-Dist: dateparser
Requires-Dist: motor (>=2.0.0)
Requires-Dist: requests
Requires-Dist: retrying
Requires-Dist: tqdm
